mmt_dipole_cuboid_inversion/__about__.py
mmt_dipole_cuboid_inversion/__init__.py
mmt_dipole_cuboid_inversion/cython_cuda_lib/__init__.py
mmt_dipole_cuboid_inversion/cython_cuda_lib/pop_matrix_cuda_lib.cu
mmt_dipole_cuboid_inversion/cython_cuda_lib/pop_matrix_cuda_lib.h
mmt_dipole_cuboid_inversion/cython_cuda_lib/pop_matrix_cudalib.pyx
mmt_dipole_cuboid_inversion/cython_lib/__init__.py
mmt_dipole_cuboid_inversion/cython_lib/pop_matrix_C_lib.c
mmt_dipole_cuboid_inversion/cython_lib/pop_matrix_C_lib.h
mmt_dipole_cuboid_inversion/cython_lib/pop_matrix_lib.c
mmt_dipole_cuboid_inversion/cython_lib/pop_matrix_lib.cp39-win_amd64.pyd
mmt_dipole_cuboid_inversion/cython_lib/pop_matrix_lib.pyx
mmt_dipole_cuboid_inversion/dipole_cuboid_inversion.py
mmt_dipole_cuboid_inversion/inversion_tools.py
mmt_dipole_cuboid_inversion/numba_lib.py
mmt_dipole_cuboid_inversion/tools/__init__.py
mmt_dipole_cuboid_inversion/tools/cuboid_decompose.py
mmt_dipole_cuboid_inversion/tools/plot.py
mmt_dipole_cuboid_inversion_config.py
mmt_dipole_cuboid_inversion-1.0.dist-info/LICENSE
mmt_dipole_cuboid_inversion-1.0.dist-info/METADATA
mmt_dipole_cuboid_inversion-1.0.dist-info/WHEEL
mmt_dipole_cuboid_inversion-1.0.dist-info/RECORD
