Metadata-Version: 2.1
Name: mmt-dipole-cuboid-inversion
Version: 1.0
Summary: Python lib to calculate the magnetization of grains using the dipole cuboids model
License: MIT
Author: F. Out
Author-email: f.out@students.uu.nl
Requires-Python: >=3.8,<3.11
Classifier: License :: OSI Approved :: MIT License
Classifier: Programming Language :: Python :: 3
Classifier: Programming Language :: Python :: 3.8
Classifier: Programming Language :: Python :: 3.9
Classifier: Programming Language :: Python :: 3.10
Requires-Dist: cython (>=0.29.26)
Requires-Dist: descartes (>=1.0)
Requires-Dist: numba (>=0.55.2)
Requires-Dist: numpy (>=1.23)
Requires-Dist: pathlib (>=1.0)
Requires-Dist: scipy (>=1.7)
Requires-Dist: shapely (>=1.7)
